tinyquery/__init__.py
tinyquery/api_client.py
tinyquery/api_client_test.py
tinyquery/compiler.py
tinyquery/compiler_test.py
tinyquery/context.py
tinyquery/evaluator.py
tinyquery/evaluator_test.py
tinyquery/exceptions.py
tinyquery/lexer.py
tinyquery/lexer_test.py
tinyquery/parser.py
tinyquery/parser_test.py
tinyquery/parsetab.py
tinyquery/repeated_util.py
tinyquery/runtime.py
tinyquery/tinyquery.py
tinyquery/tinyquery_test.py
tinyquery/tq_ast.py
tinyquery/tq_modes.py
tinyquery/tq_types.py
tinyquery/type_context.py
tinyquery/typed_ast.py
Tinyquery-1.2.2.dist-info/LICENSE
Tinyquery-1.2.2.dist-info/METADATA
Tinyquery-1.2.2.dist-info/WHEEL
Tinyquery-1.2.2.dist-info/top_level.txt
Tinyquery-1.2.2.dist-info/RECORD
