Metadata-Version: 2.1
Name: Tinyquery
Version: 1.2.2
Summary: In-memory test stub for bigquery
Home-page: https://github.com/Khan/tinyquery
Author: Khan Academy
Author-email: opensource+pypi@khanacademy.org
License: UNKNOWN
Keywords: bigquery
Platform: UNKNOWN
Classifier: License :: OSI Approved :: MIT License
Classifier: Programming Language :: Python :: 2
Classifier: Programming Language :: Python :: 2.7
Requires-Dist: arrow (>=0.12.1)
Requires-Dist: ply (>=3.10)
Requires-Dist: six (>=1.11.0)
